{
    "sourceFile": "velvet_aura/velvet_aura/settings.py",
    "activeCommit": 0,
    "commits": [
        {
            "activePatchIndex": 4,
            "patches": [
                {
                    "date": 1735508625469,
                    "content": "Index: \n===================================================================\n--- \n+++ \n"
                },
                {
                    "date": 1735509174910,
                    "content": "Index: \n===================================================================\n--- \n+++ \n@@ -11,12 +11,17 @@\n \"\"\"\n \n from pathlib import Path\n \n+import os\n+\n+from .jazzmin import JAZZMIN_SETTINGS\n+\n # Build paths inside the project like this: BASE_DIR / 'subdir'.\n BASE_DIR = Path(__file__).resolve().parent.parent\n+TEMPLATES_DIR = os.path.join(BASE_DIR, 'templates')\n+STATIC_DIR = os.path.join(BASE_DIR, 'static')\n \n-\n # Quick-start development settings - unsuitable for production\n # See https://docs.djangoproject.com/en/4.2/howto/deployment/checklist/\n \n # SECURITY WARNING: keep the secret key used in production secret!\n@@ -37,11 +42,28 @@\n     'django.contrib.sessions',\n     'django.contrib.messages',\n     'django.contrib.staticfiles',\n     'spa',\n+    'crispy_forms',\n+    'crispy_bootstrap5',\n \n ]\n \n+\n+\n+\n+\n+\n+MEDIA_URL = '/media/'  # URL to access media files\n+MEDIA_ROOT = os.path.join(BASE_DIR, 'media')  # Path to save media files locally\n+\n+\n+\n+CRISPY_ALLOWED_TEMPLATE_PACKS = 'bootstrap5'\n+CRISPY_TEMPLATE_PACK = 'bootstrap5'\n+\n+\n+\n MIDDLEWARE = [\n     'django.middleware.security.SecurityMiddleware',\n     'django.contrib.sessions.middleware.SessionMiddleware',\n     'django.middleware.common.CommonMiddleware',\n@@ -55,9 +77,9 @@\n \n TEMPLATES = [\n     {\n         'BACKEND': 'django.template.backends.django.DjangoTemplates',\n-        'DIRS': [],\n+        'DIRS': [os.path.join(BASE_DIR, 'templates')],  # Add your custom template directory here\n         'APP_DIRS': True,\n         'OPTIONS': {\n             'context_processors': [\n                 'django.template.context_processors.debug',\n"
                },
                {
                    "date": 1735509218625,
                    "content": "Index: \n===================================================================\n--- \n+++ \n@@ -139,9 +139,24 @@\n # Static files (CSS, JavaScript, Images)\n # https://docs.djangoproject.com/en/4.2/howto/static-files/\n \n STATIC_URL = 'static/'\n+STATICFILES_DIRS = [\n+    os.path.join(BASE_DIR, 'static'),\n+]\n \n+STATIC_ROOT = BASE_DIR / 'staticfiles'\n+\n+MEDIA_ROOT = os.path.join(BASE_DIR, 'media')\n+MEDIA_URL = '/media/'\n+\n+\n # Default primary key field type\n # https://docs.djangoproject.com/en/4.2/ref/settings/#default-auto-field\n \n DEFAULT_AUTO_FIELD = 'django.db.models.BigAutoField'\n+\n+\n+JAZZMIN_SETTINGS = JAZZMIN_SETTINGS\n+\n+# Add the message storage backends to your settings\n+MESSAGE_STORAGE = 'django.contrib.messages.storage.session.SessionStorage'\n"
                },
                {
                    "date": 1735509744074,
                    "content": "Index: \n===================================================================\n--- \n+++ \n@@ -52,13 +52,10 @@\n \n \n \n \n-MEDIA_URL = '/media/'  # URL to access media files\n-MEDIA_ROOT = os.path.join(BASE_DIR, 'media')  # Path to save media files locally\n \n \n-\n CRISPY_ALLOWED_TEMPLATE_PACKS = 'bootstrap5'\n CRISPY_TEMPLATE_PACK = 'bootstrap5'\n \n \n"
                },
                {
                    "date": 1735511376267,
                    "content": "Index: \n===================================================================\n--- \n+++ \n@@ -35,8 +35,10 @@\n \n # Application definition\n \n INSTALLED_APPS = [\n+    'jazzmin',\n+\n     'django.contrib.admin',\n     'django.contrib.auth',\n     'django.contrib.contenttypes',\n     'django.contrib.sessions',\n"
                }
            ],
            "date": 1735508625469,
            "name": "Commit-0",
            "content": "\"\"\"\nDjango settings for velvet_aura project.\n\nGenerated by 'django-admin startproject' using Django 4.2.11.\n\nFor more information on this file, see\nhttps://docs.djangoproject.com/en/4.2/topics/settings/\n\nFor the full list of settings and their values, see\nhttps://docs.djangoproject.com/en/4.2/ref/settings/\n\"\"\"\n\nfrom pathlib import Path\n\n# Build paths inside the project like this: BASE_DIR / 'subdir'.\nBASE_DIR = Path(__file__).resolve().parent.parent\n\n\n# Quick-start development settings - unsuitable for production\n# See https://docs.djangoproject.com/en/4.2/howto/deployment/checklist/\n\n# SECURITY WARNING: keep the secret key used in production secret!\nSECRET_KEY = 'django-insecure-)(ka284dgu^x_wp1ftu%h$7#72jrv8qdk$hwa%+l7zvg16ugg^'\n\n# SECURITY WARNING: don't run with debug turned on in production!\nDEBUG = True\n\nALLOWED_HOSTS = []\n\n\n# Application definition\n\nINSTALLED_APPS = [\n    'django.contrib.admin',\n    'django.contrib.auth',\n    'django.contrib.contenttypes',\n    'django.contrib.sessions',\n    'django.contrib.messages',\n    'django.contrib.staticfiles',\n    'spa',\n\n]\n\nMIDDLEWARE = [\n    'django.middleware.security.SecurityMiddleware',\n    'django.contrib.sessions.middleware.SessionMiddleware',\n    'django.middleware.common.CommonMiddleware',\n    'django.middleware.csrf.CsrfViewMiddleware',\n    'django.contrib.auth.middleware.AuthenticationMiddleware',\n    'django.contrib.messages.middleware.MessageMiddleware',\n    'django.middleware.clickjacking.XFrameOptionsMiddleware',\n]\n\nROOT_URLCONF = 'velvet_aura.urls'\n\nTEMPLATES = [\n    {\n        'BACKEND': 'django.template.backends.django.DjangoTemplates',\n        'DIRS': [],\n        'APP_DIRS': True,\n        'OPTIONS': {\n            'context_processors': [\n                'django.template.context_processors.debug',\n                'django.template.context_processors.request',\n                'django.contrib.auth.context_processors.auth',\n                'django.contrib.messages.context_processors.messages',\n            ],\n        },\n    },\n]\n\nWSGI_APPLICATION = 'velvet_aura.wsgi.application'\n\n\n# Database\n# https://docs.djangoproject.com/en/4.2/ref/settings/#databases\n\nDATABASES = {\n    'default': {\n        'ENGINE': 'django.db.backends.sqlite3',\n        'NAME': BASE_DIR / 'db.sqlite3',\n    }\n}\n\n\n# Password validation\n# https://docs.djangoproject.com/en/4.2/ref/settings/#auth-password-validators\n\nAUTH_PASSWORD_VALIDATORS = [\n    {\n        'NAME': 'django.contrib.auth.password_validation.UserAttributeSimilarityValidator',\n    },\n    {\n        'NAME': 'django.contrib.auth.password_validation.MinimumLengthValidator',\n    },\n    {\n        'NAME': 'django.contrib.auth.password_validation.CommonPasswordValidator',\n    },\n    {\n        'NAME': 'django.contrib.auth.password_validation.NumericPasswordValidator',\n    },\n]\n\n\n# Internationalization\n# https://docs.djangoproject.com/en/4.2/topics/i18n/\n\nLANGUAGE_CODE = 'en-us'\n\nTIME_ZONE = 'UTC'\n\nUSE_I18N = True\n\nUSE_TZ = True\n\n\n# Static files (CSS, JavaScript, Images)\n# https://docs.djangoproject.com/en/4.2/howto/static-files/\n\nSTATIC_URL = 'static/'\n\n# Default primary key field type\n# https://docs.djangoproject.com/en/4.2/ref/settings/#default-auto-field\n\nDEFAULT_AUTO_FIELD = 'django.db.models.BigAutoField'\n"
        }
    ]
}